HISTORY.txt
MANIFEST.in
README.rst
setup.py
collective/__init__.py
collective.recipe.moin.egg-info/PKG-INFO
collective.recipe.moin.egg-info/SOURCES.txt
collective.recipe.moin.egg-info/dependency_links.txt
collective.recipe.moin.egg-info/entry_points.txt
collective.recipe.moin.egg-info/namespace_packages.txt
collective.recipe.moin.egg-info/requires.txt
collective.recipe.moin.egg-info/top_level.txt
collective.recipe.moin.egg-info/zip-safe
collective/recipe/__init__.py
collective/recipe/moin/__init__.py
collective/recipe/moin/tests/__init__.py
collective/recipe/moin/tests/test_docs.py