Metadata-Version: 1.0
Name: collective.recipe.moin
Version: 0.7
Summary: A recipe to build a wiki site with MoinMoin
Home-page: https://github.com/pythonmexico/collective.recipe.moin
Author: Erik Rivera
Author-email: erik@rivera.pro
License: GPL
Platform: UNKNOWN
Classifier: Framework :: Buildout
Classifier: Intended Audience :: Developers
Classifier: Intended Audience :: System Administrators
Classifier: Programming Language :: Python
